jupyter_env_whitelist/__init__.py
jupyter_env_whitelist/whitelist.py
jupyter_env_whitelist-0.3.2.dist-info/LICENSE
jupyter_env_whitelist-0.3.2.dist-info/WHEEL
jupyter_env_whitelist-0.3.2.dist-info/METADATA
jupyter_env_whitelist-0.3.2.dist-info/RECORD
