Metadata-Version: 2.1
Name: jupyter-env-whitelist
Version: 0.3.2
Summary: 
License: MIT
Author: Daisuke Taniwaki
Author-email: daisuketaniwaki@gmail.com
Requires-Python: >=3.7,<4.0
Classifier: Framework :: IPython
Classifier: Framework :: Jupyter
Classifier: Intended Audience :: Developers
Classifier: Intended Audience :: Science/Research
Classifier: Intended Audience :: System Administrators
Classifier: License :: OSI Approved :: MIT License
Classifier: Programming Language :: Python
Classifier: Programming Language :: Python :: 3
Classifier: Programming Language :: Python :: 3.7
Classifier: Programming Language :: Python :: 3.8
Classifier: Programming Language :: Python :: 3.9
Requires-Dist: notebook (>=6.0,<7.0)
